{
  "title": "Emergency Care Systems",
  "topics": [
    {
      "topic": "The History of Emergency Care",
      "slides": [
        "## Emergency Care System",
        "## Emergency Medical Services",
        [
          "### Future agenda",
          "Maintain and improve the standard of care <!-- .element: class=\"fragment\" -->"
        ]
      ]
    },
    {
      "topic": "Levels of Emergency Personnel",
      "slides": [
        "## EMR vs EMT vs AEMT vs Paramedic",
        "## prehospital provider",
        "## Scope of Practice"
      ]
    },
    {
      "topic": "Emergency Facilities",
      "slides": []
    },
    {
      "topic": "Continutity of Care",
      "slides": []
    },
    {
      "topic": "The Importance of Commonality in Emergency Care",
      "slides": [
        "## Everyone can do something",
        "## Give everyone a task"
      ]
    },
    {
      "topic": "The Relationship of Emergency Care Systems to Public Health",
      "slides": []
    },
    {
      "topic": "The Role of Research in Emergency Care Systems",
      "slides": []
    },
    {
      "topic": "Communication Systems in Emergency Care Systems",
      "slides": [
        [
          "### Radio Etiquitte",
          "- terse and precise",
          "- adhere to local standards"
        ]
      ]
    },
    {
      "topic": "Medical Oversight in Emergency Care Systems",
      "slides": []
    },
    {
      "topic": "Emergency Care Protocols",
      "slides": []
    },
    {
      "topic": "The Importance of Documentation in Emergency Care",
      "slides": []
    },
    {
      "topic": "Quality Improvement in Emergency Care Systems",
      "slides": []
    },
    {
      "topic": "Continuing Education in Emergency Care",
      "slides": []
    }
  ]
}